<?xml version = '1.0' encoding = 'UTF-8'?>
<FKIndexAssociation class="oracle.dbtools.crest.model.design.relational.FKIndexAssociation" directorySegmentName="seg_0" id="E300E584-8B4C-6787-B85C-60EFBEDC7995" name="subjectAssessment_subject_FK">
<createdBy>joquendo</createdBy>
<createdTime>2015-04-27 21:50:50 UTC</createdTime>
<generatorID>Generado por el Usuario</generatorID>
<ownerDesignName>ERD_Core</ownerDesignName>
<containerWithKeyObject>71F1CB4E-BA9E-8BB8-D395-3737269FACCE</containerWithKeyObject>
<deleteRule>NO ACTION</deleteRule>
<localFKIndex>61CED746-E8E9-15DE-B48F-7BAC34DAECD2</localFKIndex>
<keyObject>ED8FA3C6-6434-217D-2B93-629639FF5194</keyObject>
<mandatory>true</mandatory>
<transferable>true</transferable>
<columnDependencyConstraintGenerateInDDL>true</columnDependencyConstraintGenerateInDDL>
</FKIndexAssociation>